odoo/addons/l10n_nl_account_tax_unece/README.rst
odoo/addons/l10n_nl_account_tax_unece/__init__.py
odoo/addons/l10n_nl_account_tax_unece/__manifest__.py
odoo/addons/l10n_nl_account_tax_unece/post_install.py
odoo/addons/l10n_nl_account_tax_unece/data/account_tax_template.xml
odoo/addons/l10n_nl_account_tax_unece/models/__init__.py
odoo/addons/l10n_nl_account_tax_unece/models/res_company.py
odoo/addons/l10n_nl_account_tax_unece/static/description/icon.png
odoo/addons/l10n_nl_account_tax_unece/tests/__init__.py
odoo/addons/l10n_nl_account_tax_unece/tests/test_nl_account_tax_unece.py
odoo11_addon_l10n_nl_account_tax_unece-11.0.1.0.0.dist-info/DESCRIPTION.rst
odoo11_addon_l10n_nl_account_tax_unece-11.0.1.0.0.dist-info/METADATA
odoo11_addon_l10n_nl_account_tax_unece-11.0.1.0.0.dist-info/RECORD
odoo11_addon_l10n_nl_account_tax_unece-11.0.1.0.0.dist-info/WHEEL
odoo11_addon_l10n_nl_account_tax_unece-11.0.1.0.0.dist-info/metadata.json
odoo11_addon_l10n_nl_account_tax_unece-11.0.1.0.0.dist-info/top_level.txt
